src/traffic_light.v
module traffic_light (
    input clk,
    input reset,
    output reg [2:0] lights // {Red, Yellow, Green}
);

    // State Encoding
    parameter RED    = 2'b00;
    parameter GREEN  = 2'b01;
    parameter YELLOW = 2'b10;

    reg [1:0] current_state, next_state;

    // State Register
    always @(posedge clk or posedge reset) begin
        if (reset)
            current_state <= RED;
        else
            current_state <= next_state;
    end

    // Next State Logic + Outputs
    always @(*) begin
        case (current_state)
            RED: begin
                lights = 3'b100;  // Red ON
                next_state = GREEN;
            end
            GREEN: begin
                lights = 3'b001;  // Green ON
                next_state = YELLOW;
            end
            YELLOW: begin
                lights = 3'b010;  // Yellow ON
                next_state = RED;
            end
            default: begin
                lights = 3'b100;  // Default Red
                next_state = RED;
            end
        endcase
    end

endmodule

tb/traffic_light_tb.v
`timescale 1ns/1ps

module traffic_light_tb;
    reg clk, reset;
    wire [2:0] lights;

    // Instantiate DUT
    traffic_light dut (
        .clk(clk),
        .reset(reset),
        .lights(lights)
    );

    // Clock Generator
    always #5 clk = ~clk;  // 10ns period

    initial begin
        $dumpfile("traffic_light.vcd");
        $dumpvars(0, traffic_light_tb);

        // Init
        clk = 0;
        reset = 1;
        #10 reset = 0;

        // Run simulation
        #100 $finish;
    end
endmodule

traffic_light.vcd
$date
	Tue Aug 19 16:34:36 2025
$end
$version
	Icarus Verilog
$end
$timescale
	1ps
$end
$scope module traffic_light_tb $end
$var wire 3 ! lights [2:0] $end
$var reg 1 " clk $end
$var reg 1 # reset $end
$scope module dut $end
$var wire 1 " clk $end
$var wire 1 # reset $end
$var reg 2 $ current_state [1:0] $end
$var reg 3 % lights [2:0] $end
$var reg 2 & next_state [1:0] $end
$upscope $end
$upscope $end
$enddefinitions $end
#0
$dumpvars
b1 &
b100 %
b0 $
1#
0"
b100 !
$end
#5000
1"
#10000
0"
0#
#15000
b10 &
b1 !
b1 %
b1 $
1"
#20000
0"
#25000
b0 &
b10 !
b10 %
b10 $
1"
#30000
0"
#35000
b1 &
b100 !
b100 %
b0 $
1"
#40000
0"
#45000
b10 &
b1 !
b1 %
b1 $
1"
#50000
0"
#55000
b0 &
b10 !
b10 %
b10 $
1"
#60000
0"
#65000
b1 &
b100 !
b100 %
b0 $
1"
#70000
0"
#75000
b10 &
b1 !
b1 %
b1 $
1"
#80000
0"
#85000
b0 &
b10 !
b10 %
b10 $
1"
#90000
0"
#95000
b1 &
b100 !
b100 %
b0 $
1"
#100000
0"
#105000
b10 &
b1 !
b1 %
b1 $
1"
